{"verbs": [{"verb": "spent", "description": "[ARG0: i] [V: spent] [ARG1: 5 years] [ARG2: studying rich people] and here what they tend to have in common they plan their days", "tags": ["B-ARG0", "B-V", "B-ARG1", "I-ARG1", "B-ARG2", "I-ARG2", "I-ARG2", "O", "O", "O", "O", "O", "O", "O", "O", "O", "O", "O", "O", "O"]}, {"verb": "studying", "description": "[ARG0: i] spent 5 years [V: studying] [ARG1: rich people] and here what they tend to have in common they plan their days", "tags": ["B-ARG0", "O", "O", "O", "B-V", "B-ARG1", "I-ARG1", "O", "O", "O", "O", "O", "O", "O", "O", "O", "O", "O", "O", "O"]}, {"verb": "tend", "description": "i spent 5 years studying rich people and here what [ARG1: they] [V: tend] [ARG2: to have in common] they plan their days", "tags": ["O", "O", "O", "O", "O", "O", "O", "O", "O", "O", "B-ARG1", "B-V", "B-ARG2", "I-ARG2", "I-ARG2", "I-ARG2", "O", "O", "O", "O"]}, {"verb": "have", "description": "i spent 5 years studying rich people and here [ARG1: what] [ARG0: they] tend to [V: have] [ARGM-ADV: in common] they plan their days", "tags": ["O", "O", "O", "O", "O", "O", "O", "O", "O", "B-ARG1", "B-ARG0", "O", "O", "B-V", "B-ARGM-ADV", "I-ARGM-ADV", "O", "O", "O", "O"]}, {"verb": "plan", "description": "i spent 5 years studying rich people and [ARGM-LOC: here what they tend to have in common] [ARG0: they] [V: plan] [ARG1: their days]", "tags": ["O", "O", "O", "O", "O", "O", "O", "O", "B-ARGM-LOC", "I-ARGM-LOC", "I-ARGM-LOC", "I-ARGM-LOC", "I-ARGM-LOC", "I-ARGM-LOC", "I-ARGM-LOC", "I-ARGM-LOC", "B-ARG0", "B-V", "B-ARG1", "I-ARG1"]}], "words": ["i", "spent", "5", "years", "studying", "rich", "people", "and", "here", "what", "they", "tend", "to", "have", "in", "common", "they", "plan", "their", "days"]}