{"verbs": [{"verb": "is", "description": "[V: is] [ARG1: this] [ARG2: the last photo ever taken of jfk the zapruder film captured the assassination on 8 mm home - movie film but the last still photograph taken of jfk was something else dallas president john f kennedy warren commission abraham zapruder president john f kennedy]", "tags": ["B-V", "B-ARG1", "B-ARG2", "I-ARG2", "I-ARG2", "I-ARG2", "I-ARG2", "I-ARG2", "I-ARG2", "I-ARG2", "I-ARG2", "I-ARG2", "I-ARG2", "I-ARG2", "I-ARG2", "I-ARG2", "I-ARG2", "I-ARG2", "I-ARG2", "I-ARG2", "I-ARG2", "I-ARG2", "I-ARG2", "I-ARG2", "I-ARG2", "I-ARG2", "I-ARG2", "I-ARG2", "I-ARG2", "I-ARG2", "I-ARG2", "I-ARG2", "I-ARG2", "I-ARG2", "I-ARG2", "I-ARG2", "I-ARG2", "I-ARG2", "I-ARG2", "I-ARG2", "I-ARG2", "I-ARG2", "I-ARG2", "I-ARG2", "I-ARG2", "I-ARG2"]}, {"verb": "taken", "description": "is this [ARG1: the last photo] [ARGM-TMP: ever] [V: taken] of jfk the zapruder film captured the assassination on 8 mm home - movie film but the last still photograph taken of jfk was something else dallas president john f kennedy warren commission abraham zapruder president john f kennedy", "tags": ["O", "O", "B-ARG1", "I-ARG1", "I-ARG1", "B-ARGM-TMP", "B-V", "O", "O", "O", "O", "O", "O", "O", "O", "O", "O", "O", "O", "O", "O", "O", "O", "O", "O", "O", "O", "O", "O", "O", "O", "O", "O", "O", "O", "O", "O", "O", "O", "O", "O", "O", "O", "O", "O", "O"]}, {"verb": "captured", "description": "is this the last photo ever taken of jfk [ARG0: the zapruder film] [V: captured] [ARG1: the assassination on 8 mm home - movie film] but the last still photograph taken of jfk was something else dallas president john f kennedy warren commission abraham zapruder president john f kennedy", "tags": ["O", "O", "O", "O", "O", "O", "O", "O", "O", "B-ARG0", "I-ARG0", "I-ARG0", "B-V", "B-ARG1", "I-ARG1", "I-ARG1", "I-ARG1", "I-ARG1", "I-ARG1", "I-ARG1", "I-ARG1", "I-ARG1", "O", "O", "O", "O", "O", "O", "O", "O", "O", "O", "O", "O", "O", "O", "O", "O", "O", "O", "O", "O", "O", "O", "O", "O"]}, {"verb": "photograph", "description": "is this the last photo ever taken of jfk the zapruder film captured the assassination on 8 mm home - movie film but the [ARGM-TMP: last] [ARGM-TMP: still] [V: photograph] taken of jfk was something else dallas president john f kennedy warren commission abraham zapruder president john f kennedy", "tags": ["O", "O", "O", "O", "O", "O", "O", "O", "O", "O", "O", "O", "O", "O", "O", "O", "O", "O", "O", "O", "O", "O", "O", "O", "B-ARGM-TMP", "B-ARGM-TMP", "B-V", "O", "O", "O", "O", "O", "O", "O", "O", "O", "O", "O", "O", "O", "O", "O", "O", "O", "O", "O"]}, {"verb": "taken", "description": "is this the last photo ever taken of jfk the zapruder film captured the assassination on 8 mm home - movie film but the last still photograph [V: taken] [ARG2: of jfk] was something else dallas president john f kennedy warren commission abraham zapruder president john f kennedy", "tags": ["O", "O", "O", "O", "O", "O", "O", "O", "O", "O", "O", "O", "O", "O", "O", "O", "O", "O", "O", "O", "O", "O", "O", "O", "O", "O", "O", "B-V", "B-ARG2", "I-ARG2", "O", "O", "O", "O", "O", "O", "O", "O", "O", "O", "O", "O", "O", "O", "O", "O"]}, {"verb": "was", "description": "is this the last photo ever taken of jfk the zapruder film captured the assassination on 8 mm home - movie film but [ARG1: the last still photograph taken of jfk] [V: was] [ARG2: something else dallas president john f kennedy warren commission abraham zapruder president john f kennedy]", "tags": ["O", "O", "O", "O", "O", "O", "O", "O", "O", "O", "O", "O", "O", "O", "O", "O", "O", "O", "O", "O", "O", "O", "O", "B-ARG1", "I-ARG1", "I-ARG1", "I-ARG1", "I-ARG1", "I-ARG1", "I-ARG1", "B-V", "B-ARG2", "I-ARG2", "I-ARG2", "I-ARG2", "I-ARG2", "I-ARG2", "I-ARG2", "I-ARG2", "I-ARG2", "I-ARG2", "I-ARG2", "I-ARG2", "I-ARG2", "I-ARG2", "I-ARG2"]}, {"verb": "dallas", "description": "is this the last photo ever taken of jfk the zapruder film captured the assassination on 8 mm home - movie film but the last still photograph taken of jfk was something else [V: dallas] president john f kennedy warren commission abraham zapruder president john f kennedy", "tags": ["O", "O", "O", "O", "O", "O", "O", "O", "O", "O", "O", "O", "O", "O", "O", "O", "O", "O", "O", "O", "O", "O", "O", "O", "O", "O", "O", "O", "O", "O", "O", "O", "O", "B-V", "O", "O", "O", "O", "O", "O", "O", "O", "O", "O", "O", "O"]}], "words": ["is", "this", "the", "last", "photo", "ever", "taken", "of", "jfk", "the", "zapruder", "film", "captured", "the", "assassination", "on", "8", "mm", "home", "-", "movie", "film", "but", "the", "last", "still", "photograph", "taken", "of", "jfk", "was", "something", "else", "dallas", "president", "john", "f", "kennedy", "warren", "commission", "abraham", "zapruder", "president", "john", "f", "kennedy"]}