{"verbs": [{"verb": "arrested", "description": "[ARG1: pharmacist] [V: arrested] 2 phoenix - area pharmacies closed in dea bust agents from the drug enforcement administration and homeland security investigations executed eight search and arrest warrants thursday in the phoenix metro area vilawoe aku boadu phoenix arizona erica curry heroin oxycodone drug enforcement administration phoenix field division us immigration and customs enforcement doug ducey michael karron holley dea", "tags": ["B-ARG1", "B-V", "O", "O", "O", "O", "O", "O", "O", "O", "O", "O", "O", "O", "O", "O", "O", "O", "O", "O", "O", "O", "O", "O", "O", "O", "O", "O", "O", "O", "O", "O", "O", "O", "O", "O", "O", "O", "O", "O", "O", "O", "O", "O", "O", "O", "O", "O", "O", "O", "O", "O", "O", "O", "O", "O", "O", "O", "O"]}, {"verb": "closed", "description": "pharmacist arrested 2 [ARG1: phoenix - area pharmacies] [V: closed] [ARGM-LOC: in dea bust agents] from the drug enforcement administration and homeland security investigations executed eight search and arrest warrants thursday in the phoenix metro area vilawoe aku boadu phoenix arizona erica curry heroin oxycodone drug enforcement administration phoenix field division us immigration and customs enforcement doug ducey michael karron holley dea", "tags": ["O", "O", "O", "B-ARG1", "I-ARG1", "I-ARG1", "I-ARG1", "B-V", "B-ARGM-LOC", "I-ARGM-LOC", "I-ARGM-LOC", "I-ARGM-LOC", "O", "O", "O", "O", "O", "O", "O", "O", "O", "O", "O", "O", "O", "O", "O", "O", "O", "O", "O", "O", "O", "O", "O", "O", "O", "O", "O", "O", "O", "O", "O", "O", "O", "O", "O", "O", "O", "O", "O", "O", "O", "O", "O", "O", "O", "O", "O"]}, {"verb": "executed", "description": "[ARG0: pharmacist] arrested 2 phoenix - area pharmacies closed in dea bust agents from the drug enforcement administration and homeland security investigations [V: executed] [ARG1: eight search and arrest warrants] [ARGM-TMP: thursday] [ARGM-LOC: in the phoenix metro area] vilawoe aku [C-ARG1: boadu phoenix arizona erica curry heroin oxycodone drug] enforcement administration phoenix field division us immigration and customs enforcement doug ducey michael karron holley dea", "tags": ["B-ARG0", "O", "O", "O", "O", "O", "O", "O", "O", "O", "O", "O", "O", "O", "O", "O", "O", "O", "O", "O", "O", "B-V", "B-ARG1", "I-ARG1", "I-ARG1", "I-ARG1", "I-ARG1", "B-ARGM-TMP", "B-ARGM-LOC", "I-ARGM-LOC", "I-ARGM-LOC", "I-ARGM-LOC", "I-ARGM-LOC", "O", "O", "B-C-ARG1", "I-C-ARG1", "I-C-ARG1", "I-C-ARG1", "I-C-ARG1", "I-C-ARG1", "I-C-ARG1", "I-C-ARG1", "O", "O", "O", "O", "O", "O", "O", "O", "O", "O", "O", "O", "O", "O", "O", "O"]}, {"verb": "erica", "description": "pharmacist arrested 2 phoenix - area pharmacies closed in dea bust agents from the drug enforcement administration and homeland security investigations executed eight search and arrest warrants thursday in the phoenix metro area vilawoe aku boadu phoenix arizona [V: erica] curry heroin oxycodone drug enforcement administration phoenix field division us immigration and customs enforcement doug ducey michael karron holley dea", "tags": ["O", "O", "O", "O", "O", "O", "O", "O", "O", "O", "O", "O", "O", "O", "O", "O", "O", "O", "O", "O", "O", "O", "O", "O", "O", "O", "O", "O", "O", "O", "O", "O", "O", "O", "O", "O", "O", "O", "B-V", "O", "O", "O", "O", "O", "O", "O", "O", "O", "O", "O", "O", "O", "O", "O", "O", "O", "O", "O", "O"]}], "words": ["pharmacist", "arrested", "2", "phoenix", "-", "area", "pharmacies", "closed", "in", "dea", "bust", "agents", "from", "the", "drug", "enforcement", "administration", "and", "homeland", "security", "investigations", "executed", "eight", "search", "and", "arrest", "warrants", "thursday", "in", "the", "phoenix", "metro", "area", "vilawoe", "aku", "boadu", "phoenix", "arizona", "erica", "curry", "heroin", "oxycodone", "drug", "enforcement", "administration", "phoenix", "field", "division", "us", "immigration", "and", "customs", "enforcement", "doug", "ducey", "michael", "karron", "holley", "dea"]}