{"verbs": [{"verb": "is", "description": "photo of this college football cheerleader [V: is] going viral week 8 of the college football season kicked off earlier this week with an appetizer of games before saturday main slate with saturday games upon us one undefeated program is on the ropes cincinnati entered this afternoon game against temple with an unblemished 6 - 0 record however the bearcats and owls are tied 10 - 10 at the \u2026 morgan calantoni milwaukee bucks cincinnati instagram football owls college football owls band donte divincenzo bearcats", "tags": ["O", "O", "O", "O", "O", "O", "B-V", "O", "O", "O", "O", "O", "O", "O", "O", "O", "O", "O", "O", "O", "O", "O", "O", "O", "O", "O", "O", "O", "O", "O", "O", "O", "O", "O", "O", "O", "O", "O", "O", "O", "O", "O", "O", "O", "O", "O", "O", "O", "O", "O", "O", "O", "O", "O", "O", "O", "O", "O", "O", "O", "O", "O", "O", "O", "O", "O", "O", "O", "O", "O", "O", "O", "O", "O", "O", "O", "O", "O", "O", "O", "O", "O", "O", "O"]}, {"verb": "going", "description": "[ARG1: photo of this college football cheerleader] is [V: going] [ARG2: viral] [ARGM-TMP: week 8 of the college football season kicked off earlier this week with an appetizer of games before saturday main slate with saturday games upon us one undefeated program is on the ropes cincinnati entered] this afternoon game against temple with an unblemished 6 - 0 record however the bearcats and owls are tied 10 - 10 at the \u2026 morgan calantoni milwaukee bucks cincinnati instagram football owls college football owls band donte divincenzo bearcats", "tags": ["B-ARG1", "I-ARG1", "I-ARG1", "I-ARG1", "I-ARG1", "I-ARG1", "O", "B-V", "B-ARG2", "B-ARGM-TMP", "I-ARGM-TMP", "I-ARGM-TMP", "I-ARGM-TMP", "I-ARGM-TMP", "I-ARGM-TMP", "I-ARGM-TMP", "I-ARGM-TMP", "I-ARGM-TMP", "I-ARGM-TMP", "I-ARGM-TMP", "I-ARGM-TMP", "I-ARGM-TMP", "I-ARGM-TMP", "I-ARGM-TMP", "I-ARGM-TMP", "I-ARGM-TMP", "I-ARGM-TMP", "I-ARGM-TMP", "I-ARGM-TMP", "I-ARGM-TMP", "I-ARGM-TMP", "I-ARGM-TMP", "I-ARGM-TMP", "I-ARGM-TMP", "I-ARGM-TMP", "I-ARGM-TMP", "I-ARGM-TMP", "I-ARGM-TMP", "I-ARGM-TMP", "I-ARGM-TMP", "I-ARGM-TMP", "I-ARGM-TMP", "I-ARGM-TMP", "I-ARGM-TMP", "O", "O", "O", "O", "O", "O", "O", "O", "O", "O", "O", "O", "O", "O", "O", "O", "O", "O", "O", "O", "O", "O", "O", "O", "O", "O", "O", "O", "O", "O", "O", "O", "O", "O", "O", "O", "O", "O", "O", "O"]}, {"verb": "kicked", "description": "photo of this college football cheerleader is going viral week 8 of [ARG1: the college football season] [V: kicked] off [ARGM-TMP: earlier this week] [ARGM-MNR: with an appetizer of games before saturday main slate with saturday games upon us one undefeated program is on the ropes] cincinnati entered this afternoon game against temple with an unblemished 6 - 0 record however the bearcats and owls are tied 10 - 10 at the \u2026 morgan calantoni milwaukee bucks cincinnati instagram football owls college football owls band donte divincenzo bearcats", "tags": ["O", "O", "O", "O", "O", "O", "O", "O", "O", "O", "O", "O", "B-ARG1", "I-ARG1", "I-ARG1", "I-ARG1", "B-V", "O", "B-ARGM-TMP", "I-ARGM-TMP", "I-ARGM-TMP", "B-ARGM-MNR", "I-ARGM-MNR", "I-ARGM-MNR", "I-ARGM-MNR", "I-ARGM-MNR", "I-ARGM-MNR", "I-ARGM-MNR", "I-ARGM-MNR", "I-ARGM-MNR", "I-ARGM-MNR", "I-ARGM-MNR", "I-ARGM-MNR", "I-ARGM-MNR", "I-ARGM-MNR", "I-ARGM-MNR", "I-ARGM-MNR", "I-ARGM-MNR", "I-ARGM-MNR", "I-ARGM-MNR", "I-ARGM-MNR", "I-ARGM-MNR", "O", "O", "O", "O", "O", "O", "O", "O", "O", "O", "O", "O", "O", "O", "O", "O", "O", "O", "O", "O", "O", "O", "O", "O", "O", "O", "O", "O", "O", "O", "O", "O", "O", "O", "O", "O", "O", "O", "O", "O", "O", "O"]}, {"verb": "is", "description": "photo of this college football cheerleader is going viral week 8 of the college football season kicked off earlier this week with an appetizer of games before saturday main slate with saturday games upon us [ARG1: one undefeated program] [V: is] [ARG2: on the ropes] cincinnati entered this afternoon game against temple with an unblemished 6 - 0 record however the bearcats and owls are tied 10 - 10 at the \u2026 morgan calantoni milwaukee bucks cincinnati instagram football owls college football owls band donte divincenzo bearcats", "tags": ["O", "O", "O", "O", "O", "O", "O", "O", "O", "O", "O", "O", "O", "O", "O", "O", "O", "O", "O", "O", "O", "O", "O", "O", "O", "O", "O", "O", "O", "O", "O", "O", "O", "O", "O", "B-ARG1", "I-ARG1", "I-ARG1", "B-V", "B-ARG2", "I-ARG2", "I-ARG2", "O", "O", "O", "O", "O", "O", "O", "O", "O", "O", "O", "O", "O", "O", "O", "O", "O", "O", "O", "O", "O", "O", "O", "O", "O", "O", "O", "O", "O", "O", "O", "O", "O", "O", "O", "O", "O", "O", "O", "O", "O", "O"]}, {"verb": "entered", "description": "photo of this college football cheerleader is going viral week 8 of the college football season kicked off earlier this week with an appetizer of games before saturday main slate with saturday games upon us one undefeated program is on the ropes cincinnati [V: entered] [ARG1: this afternoon game against temple] [ARGM-MNR: with an unblemished 6 - 0 record] however the bearcats and owls are tied 10 - 10 at the \u2026 morgan calantoni milwaukee bucks cincinnati instagram football owls college football owls band donte divincenzo bearcats", "tags": ["O", "O", "O", "O", "O", "O", "O", "O", "O", "O", "O", "O", "O", "O", "O", "O", "O", "O", "O", "O", "O", "O", "O", "O", "O", "O", "O", "O", "O", "O", "O", "O", "O", "O", "O", "O", "O", "O", "O", "O", "O", "O", "O", "B-V", "B-ARG1", "I-ARG1", "I-ARG1", "I-ARG1", "I-ARG1", "B-ARGM-MNR", "I-ARGM-MNR", "I-ARGM-MNR", "I-ARGM-MNR", "I-ARGM-MNR", "I-ARGM-MNR", "I-ARGM-MNR", "O", "O", "O", "O", "O", "O", "O", "O", "O", "O", "O", "O", "O", "O", "O", "O", "O", "O", "O", "O", "O", "O", "O", "O", "O", "O", "O", "O"]}, {"verb": "are", "description": "photo of this college football cheerleader is going viral week 8 of the college football season kicked off earlier this week with an appetizer of games before saturday main slate with saturday games upon us one undefeated program is on the ropes cincinnati entered this afternoon game against temple with an unblemished 6 - 0 record however the bearcats and owls [V: are] tied 10 - 10 at the \u2026 morgan calantoni milwaukee bucks cincinnati instagram football owls college football owls band donte divincenzo bearcats", "tags": ["O", "O", "O", "O", "O", "O", "O", "O", "O", "O", "O", "O", "O", "O", "O", "O", "O", "O", "O", "O", "O", "O", "O", "O", "O", "O", "O", "O", "O", "O", "O", "O", "O", "O", "O", "O", "O", "O", "O", "O", "O", "O", "O", "O", "O", "O", "O", "O", "O", "O", "O", "O", "O", "O", "O", "O", "O", "O", "O", "O", "O", "B-V", "O", "O", "O", "O", "O", "O", "O", "O", "O", "O", "O", "O", "O", "O", "O", "O", "O", "O", "O", "O", "O", "O"]}, {"verb": "tied", "description": "photo of this college football cheerleader is going viral week 8 of the college football season kicked off earlier this week with an appetizer of games before saturday main slate with saturday games upon us one undefeated program is on the ropes cincinnati entered this afternoon game against temple with an unblemished 6 - 0 record however [ARG1: the bearcats and owls] are [V: tied] [ARGM-EXT: 10 - 10] [ARGM-LOC: at the] \u2026 morgan calantoni milwaukee bucks cincinnati instagram football owls college football owls band donte divincenzo bearcats", "tags": ["O", "O", "O", "O", "O", "O", "O", "O", "O", "O", "O", "O", "O", "O", "O", "O", "O", "O", "O", "O", "O", "O", "O", "O", "O", "O", "O", "O", "O", "O", "O", "O", "O", "O", "O", "O", "O", "O", "O", "O", "O", "O", "O", "O", "O", "O", "O", "O", "O", "O", "O", "O", "O", "O", "O", "O", "O", "B-ARG1", "I-ARG1", "I-ARG1", "I-ARG1", "O", "B-V", "B-ARGM-EXT", "I-ARGM-EXT", "I-ARGM-EXT", "B-ARGM-LOC", "I-ARGM-LOC", "O", "O", "O", "O", "O", "O", "O", "O", "O", "O", "O", "O", "O", "O", "O", "O"]}, {"verb": "cincinnati", "description": "photo of this college football cheerleader is going viral week 8 of the college football season kicked off earlier this week with an appetizer of games before saturday main slate with saturday games upon us one undefeated program is on the ropes cincinnati entered this afternoon game against temple with an unblemished 6 - 0 record however the bearcats and owls are tied 10 - 10 at the \u2026 morgan calantoni milwaukee bucks [V: cincinnati] instagram football owls college football owls band donte divincenzo bearcats", "tags": ["O", "O", "O", "O", "O", "O", "O", "O", "O", "O", "O", "O", "O", "O", "O", "O", "O", "O", "O", "O", "O", "O", "O", "O", "O", "O", "O", "O", "O", "O", "O", "O", "O", "O", "O", "O", "O", "O", "O", "O", "O", "O", "O", "O", "O", "O", "O", "O", "O", "O", "O", "O", "O", "O", "O", "O", "O", "O", "O", "O", "O", "O", "O", "O", "O", "O", "O", "O", "O", "O", "O", "O", "O", "B-V", "O", "O", "O", "O", "O", "O", "O", "O", "O", "O"]}], "words": ["photo", "of", "this", "college", "football", "cheerleader", "is", "going", "viral", "week", "8", "of", "the", "college", "football", "season", "kicked", "off", "earlier", "this", "week", "with", "an", "appetizer", "of", "games", "before", "saturday", "main", "slate", "with", "saturday", "games", "upon", "us", "one", "undefeated", "program", "is", "on", "the", "ropes", "cincinnati", "entered", "this", "afternoon", "game", "against", "temple", "with", "an", "unblemished", "6", "-", "0", "record", "however", "the", "bearcats", "and", "owls", "are", "tied", "10", "-", "10", "at", "the", "\u2026", "morgan", "calantoni", "milwaukee", "bucks", "cincinnati", "instagram", "football", "owls", "college", "football", "owls", "band", "donte", "divincenzo", "bearcats"]}