{"verbs": [{"verb": "make", "description": "[ARG0: teens young women] [V: make] up [ARG1: 44 of knox county chlamydia cases] and numbers are up since 2013 chlamydia has been the most commonly reported sexually transmitted infection and it highest among females ages 15 - 19 and 20 - 24 tennessee knoxville tennessee knoxville usa today 44 knox county", "tags": ["B-ARG0", "I-ARG0", "I-ARG0", "B-V", "O", "B-ARG1", "I-ARG1", "I-ARG1", "I-ARG1", "I-ARG1", "I-ARG1", "O", "O", "O", "O", "O", "O", "O", "O", "O", "O", "O", "O", "O", "O", "O", "O", "O", "O", "O", "O", "O", "O", "O", "O", "O", "O", "O", "O", "O", "O", "O", "O", "O", "O", "O", "O", "O", "O"]}, {"verb": "are", "description": "teens young women make up 44 of knox county chlamydia cases and [ARG1: numbers] [V: are] [ARG2: up] [ARGM-TMP: since 2013] chlamydia has been the most commonly reported sexually transmitted infection and it highest among females ages 15 - 19 and 20 - 24 tennessee knoxville tennessee knoxville usa today 44 knox county", "tags": ["O", "O", "O", "O", "O", "O", "O", "O", "O", "O", "O", "O", "B-ARG1", "B-V", "B-ARG2", "B-ARGM-TMP", "I-ARGM-TMP", "O", "O", "O", "O", "O", "O", "O", "O", "O", "O", "O", "O", "O", "O", "O", "O", "O", "O", "O", "O", "O", "O", "O", "O", "O", "O", "O", "O", "O", "O", "O", "O"]}, {"verb": "has", "description": "teens young women make up 44 of knox county chlamydia cases and numbers are up since 2013 chlamydia [V: has] been the most commonly reported sexually transmitted infection and it highest among females ages 15 - 19 and 20 - 24 tennessee knoxville tennessee knoxville usa today 44 knox county", "tags": ["O", "O", "O", "O", "O", "O", "O", "O", "O", "O", "O", "O", "O", "O", "O", "O", "O", "O", "B-V", "O", "O", "O", "O", "O", "O", "O", "O", "O", "O", "O", "O", "O", "O", "O", "O", "O", "O", "O", "O", "O", "O", "O", "O", "O", "O", "O", "O", "O", "O"]}, {"verb": "been", "description": "teens young women make up 44 of knox county chlamydia cases and numbers are up since 2013 [ARG1: chlamydia] has [V: been] [ARG2: the most commonly reported sexually transmitted infection] and it highest among females ages 15 - 19 and 20 - 24 tennessee knoxville tennessee knoxville usa today 44 knox county", "tags": ["O", "O", "O", "O", "O", "O", "O", "O", "O", "O", "O", "O", "O", "O", "O", "O", "O", "B-ARG1", "O", "B-V", "B-ARG2", "I-ARG2", "I-ARG2", "I-ARG2", "I-ARG2", "I-ARG2", "I-ARG2", "O", "O", "O", "O", "O", "O", "O", "O", "O", "O", "O", "O", "O", "O", "O", "O", "O", "O", "O", "O", "O", "O"]}, {"verb": "reported", "description": "teens young women make up 44 of knox county chlamydia cases and numbers are up since 2013 chlamydia has been the [ARGM-TMP: most commonly] [V: reported] [ARG1: sexually transmitted infection] and it highest among females ages 15 - 19 and 20 - 24 tennessee knoxville tennessee knoxville usa today 44 knox county", "tags": ["O", "O", "O", "O", "O", "O", "O", "O", "O", "O", "O", "O", "O", "O", "O", "O", "O", "O", "O", "O", "O", "B-ARGM-TMP", "I-ARGM-TMP", "B-V", "B-ARG1", "I-ARG1", "I-ARG1", "O", "O", "O", "O", "O", "O", "O", "O", "O", "O", "O", "O", "O", "O", "O", "O", "O", "O", "O", "O", "O", "O"]}, {"verb": "transmitted", "description": "teens young women make up 44 of knox county chlamydia cases and numbers are up since 2013 chlamydia has been the most commonly reported [ARGM-MNR: sexually] [V: transmitted] [ARG1: infection] and it highest among females ages 15 - 19 and 20 - 24 tennessee knoxville tennessee knoxville usa today 44 knox county", "tags": ["O", "O", "O", "O", "O", "O", "O", "O", "O", "O", "O", "O", "O", "O", "O", "O", "O", "O", "O", "O", "O", "O", "O", "O", "B-ARGM-MNR", "B-V", "B-ARG1", "O", "O", "O", "O", "O", "O", "O", "O", "O", "O", "O", "O", "O", "O", "O", "O", "O", "O", "O", "O", "O", "O"]}, {"verb": "tennessee", "description": "teens young women make up 44 of knox county chlamydia cases and numbers are up since 2013 chlamydia has been the most commonly reported sexually transmitted infection and it highest among females ages 15 - 19 and 20 - 24 tennessee [ARG1: knoxville] [V: tennessee] knoxville usa today 44 knox county", "tags": ["O", "O", "O", "O", "O", "O", "O", "O", "O", "O", "O", "O", "O", "O", "O", "O", "O", "O", "O", "O", "O", "O", "O", "O", "O", "O", "O", "O", "O", "O", "O", "O", "O", "O", "O", "O", "O", "O", "O", "O", "O", "B-ARG1", "B-V", "O", "O", "O", "O", "O", "O"]}, {"verb": "usa", "description": "teens young women make up 44 of knox county chlamydia cases and numbers are up since 2013 chlamydia has been the most commonly reported sexually transmitted infection and it highest among females ages 15 - 19 and 20 - 24 tennessee knoxville tennessee [ARG1: knoxville] [V: usa] today 44 knox county", "tags": ["O", "O", "O", "O", "O", "O", "O", "O", "O", "O", "O", "O", "O", "O", "O", "O", "O", "O", "O", "O", "O", "O", "O", "O", "O", "O", "O", "O", "O", "O", "O", "O", "O", "O", "O", "O", "O", "O", "O", "O", "O", "O", "O", "B-ARG1", "B-V", "O", "O", "O", "O"]}], "words": ["teens", "young", "women", "make", "up", "44", "of", "knox", "county", "chlamydia", "cases", "and", "numbers", "are", "up", "since", "2013", "chlamydia", "has", "been", "the", "most", "commonly", "reported", "sexually", "transmitted", "infection", "and", "it", "highest", "among", "females", "ages", "15", "-", "19", "and", "20", "-", "24", "tennessee", "knoxville", "tennessee", "knoxville", "usa", "today", "44", "knox", "county"]}