{"verbs": [{"verb": "roswell", "description": "[V: roswell] [ARG1: piano teacher indicted on molestation charges] a fulton county grand jury has indicted a roswell piano teacher on charges he molested three of his students roswell police department roswell roswell georgia troy lawrence palmer piano lawrence palmer lisa holland", "tags": ["B-V", "B-ARG1", "I-ARG1", "I-ARG1", "I-ARG1", "I-ARG1", "I-ARG1", "O", "O", "O", "O", "O", "O", "O", "O", "O", "O", "O", "O", "O", "O", "O", "O", "O", "O", "O", "O", "O", "O", "O", "O", "O", "O", "O", "O", "O", "O", "O", "O", "O"]}, {"verb": "indicted", "description": "roswell [ARG1: piano teacher] [V: indicted] [ARG2: on molestation charges] a fulton county grand jury has indicted a roswell piano teacher on charges he molested three of his students roswell police department roswell roswell georgia troy lawrence palmer piano lawrence palmer lisa holland", "tags": ["O", "B-ARG1", "I-ARG1", "B-V", "B-ARG2", "I-ARG2", "I-ARG2", "O", "O", "O", "O", "O", "O", "O", "O", "O", "O", "O", "O", "O", "O", "O", "O", "O", "O", "O", "O", "O", "O", "O", "O", "O", "O", "O", "O", "O", "O", "O", "O", "O"]}, {"verb": "has", "description": "roswell piano teacher indicted on molestation charges a fulton county grand jury [V: has] indicted a roswell piano teacher on charges he molested three of his students roswell police department roswell roswell georgia troy lawrence palmer piano lawrence palmer lisa holland", "tags": ["O", "O", "O", "O", "O", "O", "O", "O", "O", "O", "O", "O", "B-V", "O", "O", "O", "O", "O", "O", "O", "O", "O", "O", "O", "O", "O", "O", "O", "O", "O", "O", "O", "O", "O", "O", "O", "O", "O", "O", "O"]}, {"verb": "indicted", "description": "roswell piano teacher indicted on molestation charges [ARG0: a fulton county grand jury] has [V: indicted] [ARG1: a roswell piano teacher] [ARG2: on charges he molested three of his students roswell police department roswell roswell georgia troy lawrence palmer piano lawrence palmer lisa holland]", "tags": ["O", "O", "O", "O", "O", "O", "O", "B-ARG0", "I-ARG0", "I-ARG0", "I-ARG0", "I-ARG0", "O", "B-V", "B-ARG1", "I-ARG1", "I-ARG1", "I-ARG1", "B-ARG2", "I-ARG2", "I-ARG2", "I-ARG2", "I-ARG2", "I-ARG2", "I-ARG2", "I-ARG2", "I-ARG2", "I-ARG2", "I-ARG2", "I-ARG2", "I-ARG2", "I-ARG2", "I-ARG2", "I-ARG2", "I-ARG2", "I-ARG2", "I-ARG2", "I-ARG2", "I-ARG2", "I-ARG2"]}, {"verb": "molested", "description": "roswell piano teacher indicted on molestation charges a fulton county grand jury has indicted a roswell piano teacher on charges [ARG0: he] [V: molested] [ARG1: three of his students] roswell police department roswell roswell georgia troy lawrence palmer piano lawrence palmer lisa holland", "tags": ["O", "O", "O", "O", "O", "O", "O", "O", "O", "O", "O", "O", "O", "O", "O", "O", "O", "O", "O", "O", "B-ARG0", "B-V", "B-ARG1", "I-ARG1", "I-ARG1", "I-ARG1", "O", "O", "O", "O", "O", "O", "O", "O", "O", "O", "O", "O", "O", "O"]}, {"verb": "roswell", "description": "roswell piano teacher indicted on molestation charges a fulton county grand jury has indicted a roswell piano teacher on charges he molested three of his students [V: roswell] [ARG1: police department] roswell roswell georgia troy lawrence palmer piano lawrence palmer lisa holland", "tags": ["O", "O", "O", "O", "O", "O", "O", "O", "O", "O", "O", "O", "O", "O", "O", "O", "O", "O", "O", "O", "O", "O", "O", "O", "O", "O", "B-V", "B-ARG1", "I-ARG1", "O", "O", "O", "O", "O", "O", "O", "O", "O", "O", "O"]}], "words": ["roswell", "piano", "teacher", "indicted", "on", "molestation", "charges", "a", "fulton", "county", "grand", "jury", "has", "indicted", "a", "roswell", "piano", "teacher", "on", "charges", "he", "molested", "three", "of", "his", "students", "roswell", "police", "department", "roswell", "roswell", "georgia", "troy", "lawrence", "palmer", "piano", "lawrence", "palmer", "lisa", "holland"]}