{"verbs": [{"verb": "is", "description": "sonny gray [V: is] likely done as a yankee after proving to be a bronx bust luke voit the frontrunner for starting at 1b brian cashman all but confirmed the struggling sonny gray is on the trade block brian cashman luke voit the bronx new york yankees bronx gm sonny gray yankees", "tags": ["O", "O", "B-V", "O", "O", "O", "O", "O", "O", "O", "O", "O", "O", "O", "O", "O", "O", "O", "O", "O", "O", "O", "O", "O", "O", "O", "O", "O", "O", "O", "O", "O", "O", "O", "O", "O", "O", "O", "O", "O", "O", "O", "O", "O", "O", "O", "O", "O", "O", "O", "O"]}, {"verb": "done", "description": "[ARG1: sonny gray] is [ARGM-ADV: likely] [V: done] [ARGM-MNR: as a yankee] [ARGM-TMP: after proving to be a bronx bust] luke voit the frontrunner for starting at 1b brian cashman all but confirmed the struggling sonny gray is on the trade block brian cashman luke voit the bronx new york yankees bronx gm sonny gray yankees", "tags": ["B-ARG1", "I-ARG1", "O", "B-ARGM-ADV", "B-V", "B-ARGM-MNR", "I-ARGM-MNR", "I-ARGM-MNR", "B-ARGM-TMP", "I-ARGM-TMP", "I-ARGM-TMP", "I-ARGM-TMP", "I-ARGM-TMP", "I-ARGM-TMP", "I-ARGM-TMP", "O", "O", "O", "O", "O", "O", "O", "O", "O", "O", "O", "O", "O", "O", "O", "O", "O", "O", "O", "O", "O", "O", "O", "O", "O", "O", "O", "O", "O", "O", "O", "O", "O", "O", "O", "O"]}, {"verb": "proving", "description": "sonny gray is likely done as a yankee after [V: proving] [ARG1: to be a bronx bust] luke voit the frontrunner for starting at 1b brian cashman all but confirmed the struggling sonny gray is on the trade block brian cashman luke voit the bronx new york yankees bronx gm sonny gray yankees", "tags": ["O", "O", "O", "O", "O", "O", "O", "O", "O", "B-V", "B-ARG1", "I-ARG1", "I-ARG1", "I-ARG1", "I-ARG1", "O", "O", "O", "O", "O", "O", "O", "O", "O", "O", "O", "O", "O", "O", "O", "O", "O", "O", "O", "O", "O", "O", "O", "O", "O", "O", "O", "O", "O", "O", "O", "O", "O", "O", "O", "O"]}, {"verb": "be", "description": "sonny gray is likely done as a yankee after proving to [V: be] [ARG2: a bronx bust] luke voit the frontrunner for starting at 1b brian cashman all but confirmed the struggling sonny gray is on the trade block brian cashman luke voit the bronx new york yankees bronx gm sonny gray yankees", "tags": ["O", "O", "O", "O", "O", "O", "O", "O", "O", "O", "O", "B-V", "B-ARG2", "I-ARG2", "I-ARG2", "O", "O", "O", "O", "O", "O", "O", "O", "O", "O", "O", "O", "O", "O", "O", "O", "O", "O", "O", "O", "O", "O", "O", "O", "O", "O", "O", "O", "O", "O", "O", "O", "O", "O", "O", "O"]}, {"verb": "starting", "description": "sonny gray is likely done as a yankee after proving to be a bronx bust luke voit the frontrunner for [V: starting] [ARGM-LOC: at 1b] brian cashman all but confirmed the struggling sonny gray is on the trade block brian cashman luke voit the bronx new york yankees bronx gm sonny gray yankees", "tags": ["O", "O", "O", "O", "O", "O", "O", "O", "O", "O", "O", "O", "O", "O", "O", "O", "O", "O", "O", "O", "B-V", "B-ARGM-LOC", "I-ARGM-LOC", "O", "O", "O", "O", "O", "O", "O", "O", "O", "O", "O", "O", "O", "O", "O", "O", "O", "O", "O", "O", "O", "O", "O", "O", "O", "O", "O", "O"]}, {"verb": "confirmed", "description": "sonny gray is likely done as a yankee after proving to be a bronx bust luke voit the frontrunner for starting at 1b [ARG0: brian cashman] [ARGM-ADV: all but] [V: confirmed] [ARG1: the struggling sonny gray is on the trade block brian cashman] luke voit the bronx new york yankees bronx gm sonny gray yankees", "tags": ["O", "O", "O", "O", "O", "O", "O", "O", "O", "O", "O", "O", "O", "O", "O", "O", "O", "O", "O", "O", "O", "O", "O", "B-ARG0", "I-ARG0", "B-ARGM-ADV", "I-ARGM-ADV", "B-V", "B-ARG1", "I-ARG1", "I-ARG1", "I-ARG1", "I-ARG1", "I-ARG1", "I-ARG1", "I-ARG1", "I-ARG1", "I-ARG1", "I-ARG1", "O", "O", "O", "O", "O", "O", "O", "O", "O", "O", "O", "O"]}, {"verb": "struggling", "description": "sonny gray is likely done as a yankee after proving to be a bronx bust luke voit the frontrunner for starting at 1b brian cashman all but confirmed the [V: struggling] [ARG0: sonny gray] is on the trade block brian cashman luke voit the bronx new york yankees bronx gm sonny gray yankees", "tags": ["O", "O", "O", "O", "O", "O", "O", "O", "O", "O", "O", "O", "O", "O", "O", "O", "O", "O", "O", "O", "O", "O", "O", "O", "O", "O", "O", "O", "O", "B-V", "B-ARG0", "I-ARG0", "O", "O", "O", "O", "O", "O", "O", "O", "O", "O", "O", "O", "O", "O", "O", "O", "O", "O", "O"]}, {"verb": "is", "description": "sonny gray is likely done as a yankee after proving to be a bronx bust luke voit the frontrunner for starting at 1b brian cashman all but confirmed [ARG1: the struggling sonny gray] [V: is] [ARG2: on the trade block] [ARGM-DIS: brian] cashman luke voit the bronx new york yankees bronx gm sonny gray yankees", "tags": ["O", "O", "O", "O", "O", "O", "O", "O", "O", "O", "O", "O", "O", "O", "O", "O", "O", "O", "O", "O", "O", "O", "O", "O", "O", "O", "O", "O", "B-ARG1", "I-ARG1", "I-ARG1", "I-ARG1", "B-V", "B-ARG2", "I-ARG2", "I-ARG2", "I-ARG2", "B-ARGM-DIS", "O", "O", "O", "O", "O", "O", "O", "O", "O", "O", "O", "O", "O"]}], "words": ["sonny", "gray", "is", "likely", "done", "as", "a", "yankee", "after", "proving", "to", "be", "a", "bronx", "bust", "luke", "voit", "the", "frontrunner", "for", "starting", "at", "1b", "brian", "cashman", "all", "but", "confirmed", "the", "struggling", "sonny", "gray", "is", "on", "the", "trade", "block", "brian", "cashman", "luke", "voit", "the", "bronx", "new", "york", "yankees", "bronx", "gm", "sonny", "gray", "yankees"]}