{"verbs": [{"verb": "sign", "description": "[ARG0: suns] [V: sign] [ARG1: crawford] [ARG2: to 1-year contract] jamal crawford 38 is entering his 19th nba season and has a career average of 15 points per game phoenix suns national basketball association aretha franklin detroit pistons nba 1-year phoenix suns jamal crawford dallas frazier isiah thomas pistons minnesota timberwolves crawford 2004 nba finals", "tags": ["B-ARG0", "B-V", "B-ARG1", "B-ARG2", "I-ARG2", "I-ARG2", "O", "O", "O", "O", "O", "O", "O", "O", "O", "O", "O", "O", "O", "O", "O", "O", "O", "O", "O", "O", "O", "O", "O", "O", "O", "O", "O", "O", "O", "O", "O", "O", "O", "O", "O", "O", "O", "O", "O", "O", "O", "O", "O", "O", "O"]}, {"verb": "is", "description": "suns sign crawford to 1-year contract jamal crawford 38 [V: is] entering his 19th nba season and has a career average of 15 points per game phoenix suns national basketball association aretha franklin detroit pistons nba 1-year phoenix suns jamal crawford dallas frazier isiah thomas pistons minnesota timberwolves crawford 2004 nba finals", "tags": ["O", "O", "O", "O", "O", "O", "O", "O", "O", "B-V", "O", "O", "O", "O", "O", "O", "O", "O", "O", "O", "O", "O", "O", "O", "O", "O", "O", "O", "O", "O", "O", "O", "O", "O", "O", "O", "O", "O", "O", "O", "O", "O", "O", "O", "O", "O", "O", "O", "O", "O", "O"]}, {"verb": "entering", "description": "suns sign crawford to 1-year contract [ARG0: jamal crawford 38] is [V: entering] [ARG1: his 19th nba season] and has a career average of 15 points per game phoenix suns national basketball association aretha franklin detroit pistons nba 1-year phoenix suns jamal crawford dallas frazier isiah thomas pistons minnesota timberwolves crawford 2004 nba finals", "tags": ["O", "O", "O", "O", "O", "O", "B-ARG0", "I-ARG0", "I-ARG0", "O", "B-V", "B-ARG1", "I-ARG1", "I-ARG1", "I-ARG1", "O", "O", "O", "O", "O", "O", "O", "O", "O", "O", "O", "O", "O", "O", "O", "O", "O", "O", "O", "O", "O", "O", "O", "O", "O", "O", "O", "O", "O", "O", "O", "O", "O", "O", "O", "O"]}, {"verb": "has", "description": "suns sign crawford to 1-year contract [ARG0: jamal crawford 38] is entering his 19th nba season and [V: has] [ARG1: a career average of 15 points per game phoenix suns national basketball association aretha franklin detroit pistons nba 1-year phoenix suns jamal crawford dallas frazier isiah thomas pistons minnesota timberwolves crawford 2004 nba finals]", "tags": ["O", "O", "O", "O", "O", "O", "B-ARG0", "I-ARG0", "I-ARG0", "O", "O", "O", "O", "O", "O", "O", "B-V", "B-ARG1", "I-ARG1", "I-ARG1", "I-ARG1", "I-ARG1", "I-ARG1", "I-ARG1", "I-ARG1", "I-ARG1", "I-ARG1", "I-ARG1", "I-ARG1", "I-ARG1", "I-ARG1", "I-ARG1", "I-ARG1", "I-ARG1", "I-ARG1", "I-ARG1", "I-ARG1", "I-ARG1", "I-ARG1", "I-ARG1", "I-ARG1", "I-ARG1", "I-ARG1", "I-ARG1", "I-ARG1", "I-ARG1", "I-ARG1", "I-ARG1", "I-ARG1", "I-ARG1", "I-ARG1"]}, {"verb": "suns", "description": "suns sign crawford to 1-year contract jamal crawford 38 is entering his 19th nba season and has a career average of 15 points per game [ARG0: phoenix] [V: suns] [ARG1: national basketball association aretha franklin detroit pistons nba 1-year phoenix suns jamal crawford dallas frazier isiah thomas pistons minnesota timberwolves crawford 2004 nba finals]", "tags": ["O", "O", "O", "O", "O", "O", "O", "O", "O", "O", "O", "O", "O", "O", "O", "O", "O", "O", "O", "O", "O", "O", "O", "O", "O", "B-ARG0", "B-V", "B-ARG1", "I-ARG1", "I-ARG1", "I-ARG1", "I-ARG1", "I-ARG1", "I-ARG1", "I-ARG1", "I-ARG1", "I-ARG1", "I-ARG1", "I-ARG1", "I-ARG1", "I-ARG1", "I-ARG1", "I-ARG1", "I-ARG1", "I-ARG1", "I-ARG1", "I-ARG1", "I-ARG1", "I-ARG1", "I-ARG1", "I-ARG1"]}, {"verb": "suns", "description": "suns sign crawford to 1-year contract jamal crawford 38 is entering his 19th nba season and has a career average of 15 points per game phoenix suns national basketball association aretha franklin detroit pistons nba 1-year phoenix [V: suns] jamal crawford dallas frazier isiah thomas pistons minnesota timberwolves crawford 2004 nba finals", "tags": ["O", "O", "O", "O", "O", "O", "O", "O", "O", "O", "O", "O", "O", "O", "O", "O", "O", "O", "O", "O", "O", "O", "O", "O", "O", "O", "O", "O", "O", "O", "O", "O", "O", "O", "O", "O", "O", "B-V", "O", "O", "O", "O", "O", "O", "O", "O", "O", "O", "O", "O", "O"]}, {"verb": "dallas", "description": "suns sign crawford to 1-year contract jamal crawford 38 is entering his 19th nba season and has a career average of 15 points per game phoenix suns national basketball association aretha franklin detroit pistons nba 1-year phoenix suns jamal crawford [V: dallas] frazier isiah thomas pistons minnesota timberwolves crawford 2004 nba finals", "tags": ["O", "O", "O", "O", "O", "O", "O", "O", "O", "O", "O", "O", "O", "O", "O", "O", "O", "O", "O", "O", "O", "O", "O", "O", "O", "O", "O", "O", "O", "O", "O", "O", "O", "O", "O", "O", "O", "O", "O", "O", "B-V", "O", "O", "O", "O", "O", "O", "O", "O", "O", "O"]}, {"verb": "crawford", "description": "suns sign crawford to 1-year contract jamal crawford 38 is entering his 19th nba season and has a career average of 15 points per game phoenix suns national basketball association aretha franklin detroit pistons nba 1-year phoenix suns jamal crawford dallas frazier isiah thomas pistons minnesota [ARG1: timberwolves] [V: crawford] 2004 nba finals", "tags": ["O", "O", "O", "O", "O", "O", "O", "O", "O", "O", "O", "O", "O", "O", "O", "O", "O", "O", "O", "O", "O", "O", "O", "O", "O", "O", "O", "O", "O", "O", "O", "O", "O", "O", "O", "O", "O", "O", "O", "O", "O", "O", "O", "O", "O", "O", "B-ARG1", "B-V", "O", "O", "O"]}], "words": ["suns", "sign", "crawford", "to", "1-year", "contract", "jamal", "crawford", "38", "is", "entering", "his", "19th", "nba", "season", "and", "has", "a", "career", "average", "of", "15", "points", "per", "game", "phoenix", "suns", "national", "basketball", "association", "aretha", "franklin", "detroit", "pistons", "nba", "1-year", "phoenix", "suns", "jamal", "crawford", "dallas", "frazier", "isiah", "thomas", "pistons", "minnesota", "timberwolves", "crawford", "2004", "nba", "finals"]}